<?xml version="1.0"?>
<response>
  <item>
    <InputValue>Gm36635</InputValue>
    <EnsemblProteinID>-</EnsemblProteinID>
  </item>
  <item>
    <InputValue>Gm36640</InputValue>
    <EnsemblProteinID>-</EnsemblProteinID>
  </item>
  <item>
    <InputValue>Gm36660</InputValue>
    <EnsemblProteinID>-</EnsemblProteinID>
  </item>
  <item>
    <InputValue>Gm36745</InputValue>
    <EnsemblProteinID>-</EnsemblProteinID>
  </item>
  <item>
    <InputValue>Gm36752</InputValue>
    <EnsemblProteinID>-</EnsemblProteinID>
  </item>
  <item>
    <InputValue>Gm36756</InputValue>
    <EnsemblProteinID>-</EnsemblProteinID>
  </item>
  <item>
    <InputValue>Gm36799</InputValue>
    <EnsemblProteinID/>
  </item>
  <item>
    <InputValue>Gm36827</InputValue>
    <EnsemblProteinID>-</EnsemblProteinID>
  </item>
  <item>
    <InputValue>Gm36839</InputValue>
    <EnsemblProteinID>-</EnsemblProteinID>
  </item>
  <item>
    <InputValue>Gm36899</InputValue>
    <EnsemblProteinID>-</EnsemblProteinID>
  </item>
  <item>
    <InputValue>Gm36975</InputValue>
    <EnsemblProteinID>-</EnsemblProteinID>
  </item>
  <item>
    <InputValue>Gm37020</InputValue>
    <EnsemblProteinID>-</EnsemblProteinID>
  </item>
  <item>
    <InputValue>Gm37027</InputValue>
    <EnsemblProteinID>-</EnsemblProteinID>
  </item>
  <item>
    <InputValue>Gm37035</InputValue>
    <EnsemblProteinID>-</EnsemblProteinID>
  </item>
  <item>
    <InputValue>Gm37065</InputValue>
    <EnsemblProteinID>-</EnsemblProteinID>
  </item>
  <item>
    <InputValue>Gm37083</InputValue>
    <EnsemblProteinID>-</EnsemblProteinID>
  </item>
  <item>
    <InputValue>Gm37118</InputValue>
    <EnsemblProteinID>-</EnsemblProteinID>
  </item>
  <item>
    <InputValue>Gm37168</InputValue>
    <EnsemblProteinID>-</EnsemblProteinID>
  </item>
  <item>
    <InputValue>Gm37170</InputValue>
    <EnsemblProteinID>-</EnsemblProteinID>
  </item>
  <item>
    <InputValue>Gm37223</InputValue>
    <EnsemblProteinID>-</EnsemblProteinID>
  </item>
  <item>
    <InputValue>Gm37229</InputValue>
    <EnsemblProteinID>-</EnsemblProteinID>
  </item>
  <item>
    <InputValue>Gm37233</InputValue>
    <EnsemblProteinID>-</EnsemblProteinID>
  </item>
  <item>
    <InputValue>Gm37240</InputValue>
    <EnsemblProteinID>//ENSMUSP00000116393//ENSMUSP00000103315//ENSMUSP00000122964//ENSMUSP00000096588</EnsemblProteinID>
  </item>
  <item>
    <InputValue>Gm37245</InputValue>
    <EnsemblProteinID>-</EnsemblProteinID>
  </item>
  <item>
    <InputValue>Gm37294</InputValue>
    <EnsemblProteinID>-</EnsemblProteinID>
  </item>
  <item>
    <InputValue>Gm37305</InputValue>
    <EnsemblProteinID>-</EnsemblProteinID>
  </item>
  <item>
    <InputValue>Gm37306</InputValue>
    <EnsemblProteinID>-</EnsemblProteinID>
  </item>
  <item>
    <InputValue>Gm37335</InputValue>
    <EnsemblProteinID>-</EnsemblProteinID>
  </item>
  <item>
    <InputValue>Gm37350</InputValue>
    <EnsemblProteinID>-</EnsemblProteinID>
  </item>
  <item>
    <InputValue>Gm37359</InputValue>
    <EnsemblProteinID>-</EnsemblProteinID>
  </item>
  <item>
    <InputValue>Gm37362</InputValue>
    <EnsemblProteinID>-</EnsemblProteinID>
  </item>
  <item>
    <InputValue>Gm37387</InputValue>
    <EnsemblProteinID>-</EnsemblProteinID>
  </item>
  <item>
    <InputValue>Gm37401</InputValue>
    <EnsemblProteinID>-</EnsemblProteinID>
  </item>
  <item>
    <InputValue>Gm37422</InputValue>
    <EnsemblProteinID>-</EnsemblProteinID>
  </item>
  <item>
    <InputValue>Gm37459</InputValue>
    <EnsemblProteinID>-</EnsemblProteinID>
  </item>
  <item>
    <InputValue>Gm37469</InputValue>
    <EnsemblProteinID>-</EnsemblProteinID>
  </item>
  <item>
    <InputValue>Gm37494</InputValue>
    <EnsemblProteinID>-</EnsemblProteinID>
  </item>
  <item>
    <InputValue>Gm37502</InputValue>
    <EnsemblProteinID>-</EnsemblProteinID>
  </item>
  <item>
    <InputValue>Gm37552</InputValue>
    <EnsemblProteinID>-</EnsemblProteinID>
  </item>
  <item>
    <InputValue>Gm37565</InputValue>
    <EnsemblProteinID>-</EnsemblProteinID>
  </item>
  <item>
    <InputValue>Gm37584</InputValue>
    <EnsemblProteinID>-</EnsemblProteinID>
  </item>
  <item>
    <InputValue>Gm37592</InputValue>
    <EnsemblProteinID>-</EnsemblProteinID>
  </item>
  <item>
    <InputValue>Gm37634</InputValue>
    <EnsemblProteinID>-</EnsemblProteinID>
  </item>
  <item>
    <InputValue>Gm37637</InputValue>
    <EnsemblProteinID>-</EnsemblProteinID>
  </item>
  <item>
    <InputValue>Gm37640</InputValue>
    <EnsemblProteinID>-</EnsemblProteinID>
  </item>
  <item>
    <InputValue>Gm37650</InputValue>
    <EnsemblProteinID>-</EnsemblProteinID>
  </item>
  <item>
    <InputValue>Gm37696</InputValue>
    <EnsemblProteinID>-</EnsemblProteinID>
  </item>
  <item>
    <InputValue>Gm37724</InputValue>
    <EnsemblProteinID>-</EnsemblProteinID>
  </item>
  <item>
    <InputValue>Gm37748</InputValue>
    <EnsemblProteinID>-</EnsemblProteinID>
  </item>
  <item>
    <InputValue>Gm37754</InputValue>
    <EnsemblProteinID>-</EnsemblProteinID>
  </item>
  <item>
    <InputValue>Gm37756</InputValue>
    <EnsemblProteinID>-</EnsemblProteinID>
  </item>
  <item>
    <InputValue>Gm37768</InputValue>
    <EnsemblProteinID>-</EnsemblProteinID>
  </item>
  <item>
    <InputValue>Gm37787</InputValue>
    <EnsemblProteinID>-</EnsemblProteinID>
  </item>
  <item>
    <InputValue>Gm37800</InputValue>
    <EnsemblProteinID>-</EnsemblProteinID>
  </item>
  <item>
    <InputValue>Gm37821</InputValue>
    <EnsemblProteinID>-</EnsemblProteinID>
  </item>
  <item>
    <InputValue>Gm37850</InputValue>
    <EnsemblProteinID>-</EnsemblProteinID>
  </item>
  <item>
    <InputValue>Gm37855</InputValue>
    <EnsemblProteinID>-</EnsemblProteinID>
  </item>
  <item>
    <InputValue>Gm37876</InputValue>
    <EnsemblProteinID>-</EnsemblProteinID>
  </item>
  <item>
    <InputValue>Gm37885</InputValue>
    <EnsemblProteinID>-</EnsemblProteinID>
  </item>
  <item>
    <InputValue>Gm37915</InputValue>
    <EnsemblProteinID>-</EnsemblProteinID>
  </item>
  <item>
    <InputValue>Gm37933</InputValue>
    <EnsemblProteinID>-</EnsemblProteinID>
  </item>
  <item>
    <InputValue>Gm37982</InputValue>
    <EnsemblProteinID>-</EnsemblProteinID>
  </item>
  <item>
    <InputValue>Gm37986</InputValue>
    <EnsemblProteinID>-</EnsemblProteinID>
  </item>
  <item>
    <InputValue>Gm37988</InputValue>
    <EnsemblProteinID>-</EnsemblProteinID>
  </item>
  <item>
    <InputValue>Gm38025</InputValue>
    <EnsemblProteinID>-</EnsemblProteinID>
  </item>
  <item>
    <InputValue>Gm38033</InputValue>
    <EnsemblProteinID>-</EnsemblProteinID>
  </item>
  <item>
    <InputValue>Gm38037</InputValue>
    <EnsemblProteinID>-</EnsemblProteinID>
  </item>
  <item>
    <InputValue>Gm38079</InputValue>
    <EnsemblProteinID>-</EnsemblProteinID>
  </item>
  <item>
    <InputValue>Gm38096</InputValue>
    <EnsemblProteinID>-</EnsemblProteinID>
  </item>
  <item>
    <InputValue>Gm38097</InputValue>
    <EnsemblProteinID>-</EnsemblProteinID>
  </item>
  <item>
    <InputValue>Gm38100</InputValue>
    <EnsemblProteinID>-</EnsemblProteinID>
  </item>
  <item>
    <InputValue>Gm38102</InputValue>
    <EnsemblProteinID>-</EnsemblProteinID>
  </item>
  <item>
    <InputValue>Gm38134</InputValue>
    <EnsemblProteinID>-</EnsemblProteinID>
  </item>
  <item>
    <InputValue>Gm38150</InputValue>
    <EnsemblProteinID>-</EnsemblProteinID>
  </item>
  <item>
    <InputValue>Gm38155</InputValue>
    <EnsemblProteinID>-</EnsemblProteinID>
  </item>
  <item>
    <InputValue>Gm38161</InputValue>
    <EnsemblProteinID>-</EnsemblProteinID>
  </item>
  <item>
    <InputValue>Gm38186</InputValue>
    <EnsemblProteinID>-</EnsemblProteinID>
  </item>
  <item>
    <InputValue>Gm38188</InputValue>
    <EnsemblProteinID>-</EnsemblProteinID>
  </item>
  <item>
    <InputValue>Gm38246</InputValue>
    <EnsemblProteinID>-</EnsemblProteinID>
  </item>
  <item>
    <InputValue>Gm38250</InputValue>
    <EnsemblProteinID>-</EnsemblProteinID>
  </item>
  <item>
    <InputValue>Gm38287</InputValue>
    <EnsemblProteinID>-</EnsemblProteinID>
  </item>
  <item>
    <InputValue>Gm38293</InputValue>
    <EnsemblProteinID>-</EnsemblProteinID>
  </item>
  <item>
    <InputValue>Gm38304</InputValue>
    <EnsemblProteinID>-</EnsemblProteinID>
  </item>
  <item>
    <InputValue>Gm38326</InputValue>
    <EnsemblProteinID/>
  </item>
  <item>
    <InputValue>Gm38335</InputValue>
    <EnsemblProteinID>-</EnsemblProteinID>
  </item>
  <item>
    <InputValue>Gm38336</InputValue>
    <EnsemblProteinID>-</EnsemblProteinID>
  </item>
  <item>
    <InputValue>Gm38392</InputValue>
    <EnsemblProteinID>-</EnsemblProteinID>
  </item>
  <item>
    <InputValue>Gm38393</InputValue>
    <EnsemblProteinID>-</EnsemblProteinID>
  </item>
  <item>
    <InputValue>Gm38394</InputValue>
    <EnsemblProteinID>-</EnsemblProteinID>
  </item>
  <item>
    <InputValue>Gm38398</InputValue>
    <EnsemblProteinID>-</EnsemblProteinID>
  </item>
  <item>
    <InputValue>Gm38399</InputValue>
    <EnsemblProteinID>-</EnsemblProteinID>
  </item>
  <item>
    <InputValue>Gm38403</InputValue>
    <EnsemblProteinID/>
  </item>
  <item>
    <InputValue>Gm38404</InputValue>
    <EnsemblProteinID/>
  </item>
  <item>
    <InputValue>Gm38405</InputValue>
    <EnsemblProteinID>-</EnsemblProteinID>
  </item>
  <item>
    <InputValue>Gm38407</InputValue>
    <EnsemblProteinID/>
  </item>
  <item>
    <InputValue>Gm38414</InputValue>
    <EnsemblProteinID/>
  </item>
  <item>
    <InputValue>Gm38431</InputValue>
    <EnsemblProteinID>-</EnsemblProteinID>
  </item>
  <item>
    <InputValue>Gm38534</InputValue>
    <EnsemblProteinID>-</EnsemblProteinID>
  </item>
  <item>
    <InputValue>Gm38590</InputValue>
    <EnsemblProteinID>-</EnsemblProteinID>
  </item>
  <item>
    <InputValue>Gm38604</InputValue>
    <EnsemblProteinID>-</EnsemblProteinID>
  </item>
</response>
